mason_tools/__init__.py
mason_tools/event_engine.py
mason_tools/mutithread.py
mason_tools/new_thread.py
mason_tools/repeat.py
mason_tools/rpc/__init__.py
mason_tools/rpc/client.py
mason_tools/rpc/common.py
mason_tools/rpc/server.py
mason_tools-0.1.5.dist-info/METADATA
mason_tools-0.1.5.dist-info/WHEEL
mason_tools-0.1.5.dist-info/top_level.txt
mason_tools-0.1.5.dist-info/RECORD
