Metadata-Version: 2.1
Name: mason-tools
Version: 0.1.5
Summary: mason_tools.
Author: mason
License: MIT
Requires-Python: >=3.7
Requires-Dist: tzlocal
Requires-Dist: numpy
Requires-Dist: pandas
Requires-Dist: pyzmq
